focus_converter/__init__.py
focus_converter/common/__init__.py
focus_converter/common/cli_options.py
focus_converter/configs/__init__.py
focus_converter/configs/base_config.py
focus_converter/configs/string_transform_args.py
focus_converter/conversion_configs/aws/0_dimension_dtypes_S001.yaml
focus_converter/conversion_configs/aws/1_charge_category_S001.yaml
focus_converter/conversion_configs/aws/1_missing_dimension_line_item_net_unblended_cost_S001.yaml
focus_converter/conversion_configs/aws/1_missing_dimension_reservation_reservation_a_r_n_S001.yaml
focus_converter/conversion_configs/aws/1_reservation_reservation_arn_S001.yaml
focus_converter/conversion_configs/aws/1_resource_type_S001.yaml
focus_converter/conversion_configs/aws/1_resource_type_S002.yaml
focus_converter/conversion_configs/aws/1_resource_type_S003.yaml
focus_converter/conversion_configs/aws/1_savings_plan_savings_plan_arn_S001.yaml
focus_converter/conversion_configs/aws/2_resource_name_S001.yaml
focus_converter/conversion_configs/aws/3_region_S001.yaml
focus_converter/conversion_configs/aws/availability_zone_S001.yaml
focus_converter/conversion_configs/aws/billed_cost_S001.yaml
focus_converter/conversion_configs/aws/billing_account_id_S001.yaml
focus_converter/conversion_configs/aws/billing_currency_S001.yaml
focus_converter/conversion_configs/aws/billing_period_end_S001.yaml
focus_converter/conversion_configs/aws/billing_period_start_S001.yaml
focus_converter/conversion_configs/aws/charge_description_S001.yaml
focus_converter/conversion_configs/aws/charge_frequency_S001.yaml
focus_converter/conversion_configs/aws/charge_period_end_S001.yaml
focus_converter/conversion_configs/aws/charge_period_start_S001.yaml
focus_converter/conversion_configs/aws/commitment_discount_category_S001.yaml
focus_converter/conversion_configs/aws/commitment_discount_id_S001.yaml
focus_converter/conversion_configs/aws/commitment_discount_type_S001.yaml
focus_converter/conversion_configs/aws/consumed_quantity_S001.yaml
focus_converter-1.0.0.dist-info/LICENSE
focus_converter-1.0.0.dist-info/METADATA
focus_converter-1.0.0.dist-info/WHEEL
focus_converter-1.0.0.dist-info/entry_points.txt
focus_converter-1.0.0.dist-info/RECORD
