Metadata-Version: 2.1
Name: focus_converter
Version: 1.0.0
Summary: 
Author: Varun Mittal
Author-email: varunmittal91@gmail.com
Requires-Python: >=3.9,<4.0
Classifier: Programming Language :: Python :: 3
Classifier: Programming Language :: Python :: 3.9
Classifier: Programming Language :: Python :: 3.10
Classifier: Programming Language :: Python :: 3.11
Classifier: Programming Language :: Python :: 3.12
Requires-Dist: focus-validator
Requires-Dist: jinja2 (>=3.1.2,<4.0.0)
Requires-Dist: networkx (>=3.1,<4.0)
Requires-Dist: pandas (>=2.0.3,<3.0.0)
Requires-Dist: pillow (>=10.1.0,<11.0.0)
Requires-Dist: polars (==0.20.10)
Requires-Dist: pyarrow (>=14,<15)
Requires-Dist: pydantic (>=2.1.1,<3.0.0)
Requires-Dist: rich (>=13.5.2,<14.0.0)
Requires-Dist: sqlglot (>=18.7.0,<19.0.0)
Requires-Dist: tqdm (>=4.66.1,<5.0.0)
Requires-Dist: typer (>=0.9.0,<0.10.0)
